COPYING
MANIFEST.in
README
lzoconf.h
lzodefs.h
lzomodule.c
minilzo.c
minilzo.h
minilzo.py
pyproject.toml
setup.py
minilzo.egg-info/PKG-INFO
minilzo.egg-info/SOURCES.txt
minilzo.egg-info/dependency_links.txt
minilzo.egg-info/top_level.txt