Metadata-Version: 2.4
Name: minilzo
Version: 1.0
Summary: This is a python library deals with lzo files compressed with lzop.
Home-page: https://github.com/Myldero/python-minilzo
Author: ir193
Author-email: iridiummx@gmail.com
Maintainer: Myldero
License:                     GNU GENERAL PUBLIC LICENSE
Classifier: Programming Language :: Python :: 3
Classifier: Programming Language :: C
Requires-Python: >=3
License-File: COPYING
Dynamic: author
Dynamic: author-email
Dynamic: classifier
Dynamic: description
Dynamic: description-content-type
Dynamic: home-page
Dynamic: license
Dynamic: license-file
Dynamic: maintainer
Dynamic: requires-python
Dynamic: summary
